findhere/__init__.py
findhere/_version.py
findhere/findhere.py
findhere/init.py
findhere-0.1.5.dist-info/LICENSE.md
findhere-0.1.5.dist-info/METADATA
findhere-0.1.5.dist-info/WHEEL
findhere-0.1.5.dist-info/top_level.txt
findhere-0.1.5.dist-info/RECORD
