Metadata-Version: 2.1
Name: findhere
Version: 0.1.5
Summary: Locate paths using relative path names locally and in the Cloud.
Home-page: https://github.com/tarjindersingh/findhere
Author: Tarjinder Singh
Author-email: tsingh@broadinstitute.org
License: MIT license
Platform: UNKNOWN
Requires-Python: >=3.7
License-File: LICENSE.md
Requires-Dist: versioneer (>=0.18)
Requires-Dist: datatracker (>=0.2.0)
Requires-Dist: hail (>=0.2.61)
